dajiaozhi_mcp_server/__init__.py
dajiaozhi_mcp_server-0.1.0.dist-info/WHEEL
dajiaozhi_mcp_server-0.1.0.dist-info/entry_points.txt
dajiaozhi_mcp_server-0.1.0.dist-info/METADATA
dajiaozhi_mcp_server-0.1.0.dist-info/RECORD
