Metadata-Version: 2.3
Name: dajiaozhi-mcp-server
Version: 0.1.0
Summary: Add your description here
Requires-Dist: mcp[cli]>=1.21.0
Requires-Python: >=3.12
